setup.py
wsgi_content_modifier/__init__.py
wsgi_content_modifier.egg-info/PKG-INFO
wsgi_content_modifier.egg-info/SOURCES.txt
wsgi_content_modifier.egg-info/dependency_links.txt
wsgi_content_modifier.egg-info/top_level.txt