Metadata-Version: 1.1
Name: wsgi-content-modifier
Version: 1.0
Summary: A WSGI base for middlewares that modifies (transforms) the response
Home-page: http://github.com/alanjds/wsgi-content-modifier
Author: Alan Justino da Silva
Author-email: alan.justino@yahoo.com.br
License: UNKNOWN
Platform: UNKNOWN
Classifier: Intended Audience :: Developers
Classifier: Operating System :: OS Independent
Classifier: Topic :: Software Development
